giant_search/__init__.py
giant_search/adapter.py
giant_search/apps.py
giant_search/mixins.py
giant_search/signals.py
giant_search/templates/search/results.html
giant_search/tests/__init__.py
giant_search/tests/test_views.py
giant_search/urls.py
giant_search/utils.py
giant_search/views.py
giant_search-1.1.7.dist-info/METADATA
giant_search-1.1.7.dist-info/WHEEL
giant_search-1.1.7.dist-info/RECORD
