Metadata-Version: 2.3
Name: giant-search
Version: 1.1.7
Summary: Provides a nice abstraction layer on top of the django-watson search library.
License: MIT
Author: Scott Pashley
Author-email: scott.pashley@giantdigital.co.uk
Requires-Python: >=3.7,<4.0
Classifier: License :: OSI Approved :: MIT License
Classifier: Programming Language :: Python :: 3
Classifier: Programming Language :: Python :: 3.7
Classifier: Programming Language :: Python :: 3.8
Classifier: Programming Language :: Python :: 3.9
Classifier: Programming Language :: Python :: 3.10
Classifier: Programming Language :: Python :: 3.11
Classifier: Programming Language :: Python :: 3.12
Classifier: Programming Language :: Python :: 3.13
Requires-Dist: django-cms (>3.11,<5.0)
Requires-Dist: django-watson (>=1.6.3,<2.0.0)
Project-URL: Homepage, https://www.giantdigital.co.uk
